{
  "brands": {
    "MLB": {
      "2025.12": {
        "Shoes": 163572560,
        "Headwear": 2463230,
        "Bag": 8872710,
        "Acc_etc": 0
      },
      "2026.01": {
        "Shoes": 0,
        "Headwear": 0,
        "Bag": 0,
        "Acc_etc": 0
      },
      "2026.02": {
        "Shoes": 221920480,
        "Headwear": 16088440,
        "Bag": 19360960,
        "Acc_etc": 1587135
      },
      "2026.03": {
        "Shoes": 166558090,
        "Headwear": 25160150,
        "Bag": 11909680,
        "Acc_etc": 38700
      },
      "2026.04": {
        "Shoes": 30350660,
        "Bag": 8554085,
        "Headwear": 9555960
      },
      "2026.05": {
        "Headwear": 0,
        "Shoes": 7166350,
        "Acc_etc": 1240380
      },
      "2026.06": {
        "Headwear": 30886580,
        "Shoes": 30776790,
        "Acc_etc": 2157450
      },
      "2026.07": {
        "Headwear": 10931040,
        "Shoes": 94967220,
        "Bag": 21720620,
        "Acc_etc": 616030
      },
      "2026.08": {
        "Headwear": 78956230,
        "Shoes": 276672840,
        "Bag": 2701635
      },
      "2026.09": {
        "Headwear": 3202080
      }
    },
    "MLB KIDS": {
      "2025.12": {
        "Shoes": 17200140,
        "Headwear": 2198021,
        "Bag": 8753269,
        "Acc_etc": 0
      },
      "2026.01": {
        "Shoes": 0,
        "Headwear": 0,
        "Bag": 0,
        "Acc_etc": 0
      },
      "2026.02": {
        "Shoes": 8756760,
        "Headwear": 3039670,
        "Bag": 0,
        "Acc_etc": 0
      },
      "2026.03": {
        "Shoes": 1883680,
        "Headwear": 44280,
        "Bag": 0,
        "Acc_etc": 0
      },
      "2026.04": {
        "Shoes": 1433050,
        "Headwear": 1476303,
        "Bag": 2575700,
        "Acc_etc": 0
      },
      "2026.05": {
        "Shoes": 0
      },
      "2026.06": {
        "Shoes": 6445450
      },
      "2026.07": {
        "Shoes": 10048080
      },
      "2026.08": {
        "Shoes": 9017160
      },
      "2026.09": {
        "Shoes": 1975950
      }
    },
    "DISCOVERY": {
      "2025.12": {
        "Shoes": 0,
        "Headwear": 370500,
        "Bag": 0,
        "Acc_etc": 0
      },
      "2026.01": {
        "Shoes": 0,
        "Headwear": 812000,
        "Bag": 432000,
        "Acc_etc": 0
      },
      "2026.02": {
        "Shoes": 0,
        "Headwear": 0,
        "Bag": 0,
        "Acc_etc": 0
      },
      "2026.03": {
        "Shoes": 0,
        "Headwear": 0,
        "Bag": 0,
        "Acc_etc": 0
      },
      "2026.04": {
        "Shoes": 0
      }
    }
  },
  "months": [
    "2025.12",
    "2026.01",
    "2026.02",
    "2026.03"
  ],
  "metadata": {
    "MLB": {
      "lastUpdated": "2026-02-10T23:38:32.083Z"
    },
    "DISCOVERY": {
      "lastUpdated": "2026-02-02T05:29:41.598Z"
    },
    "MLB KIDS": {
      "lastUpdated": "2026-02-10T23:41:42.752Z"
    }
  }
}